[
    {
        "Quarter": "Q1-2022",
        "Countries": {
            "USA": 4,
            "India": 5,
            "France": 1,
            "UK": 1,
            "Australia": 1
        },
        "Occupations": {
            "Sales": 1,
            "Operations": 1,
            "Software Engineering": 4,
            "Information Technology": 1,
            "Marketing": 1,
            "Administration": 0,
            "Human Resources": 0
        },
        "Capital": 2.04
    },
    {
        "Quarter": "Q2-2022",
        "Countries": {
            "USA": 4,
            "India": 7,
            "France": 1,
            "UK": 2,
            "Australia": 1
        },
        "Occupations": {
            "Sales": 2,
            "Operations": 2,
            "Software Engineering": 4,
            "Information Technology": 1,
            "Marketing": 1,
            "Administration": 0,
            "Human Resources": 1
        },
        "Capital": 2.04
    },
    {
        "Quarter": "Q3-2022",
        "Countries": {
            "USA": 5,
            "India": 8,
            "France": 1,
            "UK": 3,
            "Australia": 1
        },
        "Occupations": {
            "Sales": 2,
            "Operations": 3,
            "Software Engineering": 4,
            "Information Technology": 1,
            "Marketing": 1,
            "Administration": 1,
            "Human Resources": 2
        },
        "Capital": 2.04
    },
    {
        "Quarter": "Q4-2022",
        "Countries": {
            "USA": 6,
            "India": 10,
            "France": 2,
            "UK": 3,
            "Australia": 1
        },
        "Occupations": {
            "Sales": 2,
            "Operations": 3,
            "Software Engineering": 5,
            "Information Technology": 2,
            "Marketing": 1,
            "Administration": 1,
            "Human Resources": 4
        },
        "Capital": 2.04
    },
    {
        "Quarter": "Q5-2022",
        "Countries": {
            "USA": 8,
            "India": 10,
            "France": 3,
            "UK": 3,
            "Australia": 1
        },
        "Occupations": {
            "Sales": 3,
            "Operations": 3,
            "Software Engineering": 5,
            "Information Technology": 2,
            "Marketing": 1,
            "Administration": 2,
            "Human Resources": 5
        },
        "Capital": 2.04
    },
    {
        "Quarter": "Q6-2022",
        "Countries": {
            "USA": 9,
            "India": 10,
            "France": 3,
            "UK": 4,
            "Australia": 2
        },
        "Occupations": {
            "Sales": 5,
            "Operations": 3,
            "Software Engineering": 5,
            "Information Technology": 3,
            "Marketing": 1,
            "Administration": 2,
            "Human Resources": 5
        },
        "Capital": 6.76
    },
    {
        "Quarter": "Q7-2022",
        "Countries": {
            "USA": 9,
            "India": 11,
            "France": 4,
            "UK": 4,
            "Australia": 2
        },
        "Occupations": {
            "Sales": 6,
            "Operations": 3,
            "Software Engineering": 5,
            "Information Technology": 3,
            "Marketing": 1,
            "Administration": 3,
            "Human Resources": 5
        },
        "Capital": 8.85
    },
    {
        "Quarter": "Q8-2022",
        "Countries": {
            "USA": 10,
            "India": 11,
            "France": 4,
            "UK": 4,
            "Australia": 2
        },
        "Occupations": {
            "Sales": 6,
            "Operations": 3,
            "Software Engineering": 5,
            "Information Technology": 3,
            "Marketing": 1,
            "Administration": 4,
            "Human Resources": 5
        },
        "Capital": 8.85
    },
    {
        "Quarter": "Q9-2022",
        "Countries": {
            "USA": 10,
            "India": 11,
            "France": 4,
            "UK": 4,
            "Australia": 2
        },
        "Occupations": {
            "Sales": 6,
            "Operations": 3,
            "Software Engineering": 5,
            "Information Technology": 3,
            "Marketing": 1,
            "Administration": 4,
            "Human Resources": 5
        },
        "Capital": 8.85
    },
    {
        "Quarter": "Q10-2022",
        "Countries": {
            "USA": 10,
            "India": 11,
            "France": 4,
            "UK": 4,
            "Australia": 2
        },
        "Occupations": {
            "Sales": 6,
            "Operations": 3,
            "Software Engineering": 5,
            "Information Technology": 3,
            "Marketing": 1,
            "Administration": 4,
            "Human Resources": 5
        },
        "Capital": 8.85
    },
    {
        "Quarter": "Q11-2022",
        "Countries": {
            "USA": 10,
            "India": 11,
            "France": 4,
            "UK": 4,
            "Australia": 2
        },
        "Occupations": {
            "Sales": 6,
            "Operations": 3,
            "Software Engineering": 5,
            "Information Technology": 3,
            "Marketing": 1,
            "Administration": 4,
            "Human Resources": 5
        },
        "Capital": 8.85
    },
    {
        "Quarter": "Q12-2022",
        "Countries": {
            "USA": 10,
            "India": 11,
            "France": 4,
            "UK": 4,
            "Australia": 2
        },
        "Occupations": {
            "Sales": 6,
            "Operations": 3,
            "Software Engineering": 5,
            "Information Technology": 3,
            "Marketing": 1,
            "Administration": 4,
            "Human Resources": 5
        },
        "Capital": 8.85
    }
]